{
  "English": "en",
  "عربى": "ar",
  "palavra para sua língua Português Brasileiro; PT-BR": "pt",
  "Български": "bg",
  "Català": "ca",
  "Chinese (simplified)": "zh",
  "Chinese (traditional)": "zh",
  "Čeština": "cs",
  "Dansk": "da",
  "Nederlands": "nl",
  "فارسی": "fa",
  "suomeksi": "fi",
  "Français": "fr",
  "Deutsch": "de",
  "Ελληνικά": "el",
  "עברית": "he",
  "magyar": "hu",
  "Bahasa Indonesia": "id",
  "Italiano": "it",
  "Japanese": "ja",
  "한국어": "ko",
  "norsk": "no",
  "Русский": "ru",
  "español": "es",
  "Svenska": "sv",
  "ไทย": "th",
  "Türkçe": "tr",
  "tiếng Việt": "vi"
}
